egune/__init__.py
egune/interfaces.py
egune/logger.py
egune/requests.py
egune/response_manager.py
egune-0.1.44.data/scripts/egunesh
src/__init__.py
src/interfaces.py
src/logger.py
src/requests.py
egune-0.1.44.dist-info/LICENSE
egune-0.1.44.dist-info/METADATA
egune-0.1.44.dist-info/WHEEL
egune-0.1.44.dist-info/top_level.txt
egune-0.1.44.dist-info/RECORD
