Metadata-Version: 2.1
Name: egune
Version: 0.1.44
Summary: Egune Library
Home-page: UNKNOWN
Author: Bilguun Chinzorig
Author-email: bilguun@bolorsoft.com
License: UNKNOWN
Platform: UNKNOWN
Classifier: Programming Language :: Python :: 3
Classifier: License :: OSI Approved :: MIT License
Classifier: Operating System :: OS Independent
